SWTurbPy/SWTurbPy.py
SWTurbPy/__init__.py
swturbpy-0.0.8.dist-info/METADATA
swturbpy-0.0.8.dist-info/WHEEL
swturbpy-0.0.8.dist-info/licenses/LICENSE
swturbpy-0.0.8.dist-info/RECORD
