Metadata-Version: 2.4
Name: SWTurbPy
Version: 0.0.8
Summary: Basic Utilities for Solar Wind Turbulence
Project-URL: Homepage, https://github.com/huangzesen/SWTurbPy
Project-URL: Issues, https://github.com/huangzesen/SWTurbPy/issues
Author-email: Zesen Huang <huangzs1997@gmail.com>
License-File: LICENSE
Classifier: License :: OSI Approved :: MIT License
Classifier: Operating System :: OS Independent
Classifier: Programming Language :: Python :: 3
Requires-Python: <3.13,>=3.10
Requires-Dist: numba
Requires-Dist: numpy
Requires-Dist: pandas
Requires-Dist: pycwt
